torchboard/__init__.py
torchboard/base/__init__.py
torchboard/base/board.py
torchboard/base/utils.py
torchboard/dist/assets/index-C9G3_GF_.js
torchboard/dist/assets/index-xAmZYpg6.css
torchboard/dist/index.html
torchboard/operations/__init__.py
torchboard/operations/model.py
torchboard/operations/optim.py
torchboard/server/__init__.py
torchboard/server/server.py
torchboard/server/utils.py
torchboard-0.1.2.dist-info/LICENSE
torchboard-0.1.2.dist-info/METADATA
torchboard-0.1.2.dist-info/WHEEL
torchboard-0.1.2.dist-info/RECORD
