Metadata-Version: 2.3
Name: torchboard
Version: 0.1.2
Summary: Python dashboard application adding interactivity into your pytorch model
Author: Dawid Siera
Author-email: dawid.siera@gmail.com
Requires-Python: >=3.9
Classifier: Programming Language :: Python :: 3
Classifier: Programming Language :: Python :: 3.9
Classifier: Programming Language :: Python :: 3.10
Classifier: Programming Language :: Python :: 3.11
Classifier: Programming Language :: Python :: 3.12
Classifier: Programming Language :: Python :: 3.13
Requires-Dist: flask (>=3.1.0,<4.0.0)
Requires-Dist: flask-cors (>=5.0.0,<6.0.0)
Requires-Dist: flask-socketio (>=5.4.0,<6.0.0)
Requires-Dist: torch (>=2.5.1,<3.0.0)
Project-URL: Repository, https://github.com/Dawid64/Torch-Board
